MANIFEST.in
README.rst
requirements.txt
setup.py
crwyoauth/VERSION
crwyoauth/__init__.py
crwyoauth/admin.py
crwyoauth/models.py
crwyoauth/tests.py
crwyoauth/urls.py
crwyoauth/views.py
crwyoauth/locale/zh_hans/LC_MESSAGES/django.mo
crwyoauth/locale/zh_hans/LC_MESSAGES/django.po
crwyoauth/migrations/0001_initial.py
crwyoauth/migrations/__init__.py
django_crwyoauth.egg-info/PKG-INFO
django_crwyoauth.egg-info/SOURCES.txt
django_crwyoauth.egg-info/dependency_links.txt
django_crwyoauth.egg-info/not-zip-safe
django_crwyoauth.egg-info/requires.txt
django_crwyoauth.egg-info/top_level.txt