Metadata-Version: 1.0
Name: django-crwyoauth
Version: 1.0.0
Summary: OAUTH 2.0 for django
Home-page: https://github.com/wuyue92tree/django-crwyoauth
Author: wuyue
Author-email: wuyue92tree@163.com
License: BSD
Platform: UNKNOWN
